pytest_collect_formatter/__init__.py
pytest_collect_formatter/plugin.py
pytest_collect_formatter-0.4.0.dist-info/AUTHORS.rst
pytest_collect_formatter-0.4.0.dist-info/LICENSE
pytest_collect_formatter-0.4.0.dist-info/METADATA
pytest_collect_formatter-0.4.0.dist-info/WHEEL
pytest_collect_formatter-0.4.0.dist-info/entry_points.txt
pytest_collect_formatter-0.4.0.dist-info/top_level.txt
pytest_collect_formatter-0.4.0.dist-info/RECORD
