Metadata-Version: 2.1
Name: pytest-collect-formatter
Version: 0.4.0
Summary: Formatter for pytest collect output
Home-page: https://github.com/LaserPhaser/pytest-collect-formatter
Author: LaserPhaser
Author-email: arseny.antonov@gmail.com
License: MIT license
Keywords: pytest,py.test,yaml,json
Platform: UNKNOWN
Classifier: Framework :: Pytest
Classifier: Development Status :: 5 - Production/Stable
Classifier: Intended Audience :: Developers
Classifier: License :: OSI Approved :: MIT License
Classifier: Natural Language :: English
Classifier: Programming Language :: Python :: 3.6
Classifier: Programming Language :: Python :: 3.7
Classifier: Programming Language :: Python :: 3.8
Requires-Dist: dicttoxml
Requires-Dist: PyYAML
